linxo
