Metadata-Version: 2.1
Name: linxo
Version: 0.0.5
Summary: Python client for Linxo API
Home-page: https://github.com/alkivi-sas/python-linxo-client
Author: Anthony Martinet
Author-email: anthony@alkivi.fr
License: LGPLv3
Keywords: linxo
Platform: UNKNOWN
Classifier: Development Status :: 4 - Beta
Classifier: Environment :: Console
Classifier: Intended Audience :: Developers
Classifier: Topic :: Software Development :: Build Tools
Classifier: License :: OSI Approved :: GNU Lesser General Public License v3 (LGPLv3)
Classifier: Programming Language :: Python :: 2
Classifier: Programming Language :: Python :: 2.7
Classifier: Programming Language :: Python :: 3
Classifier: Programming Language :: Python :: 3.4
Classifier: Programming Language :: Python :: 3.5
Classifier: Programming Language :: Python :: 3.6
Provides-Extra: test
Provides-Extra: dev
